<?xml version="1.0" encoding="utf-8"?>
<cena version="0.6.3"><contest title="在 2008-11-2 的竞赛"><problem title="试题 1" filename="unhappy" comparetype="1" customchecker=""><input filename="unhappy.in"/><output filename="unhappy.out"/><testcase timelimit="0.1" memorylimit="256000" score="10"><input filename="unhappy\unhappy1.in"/><output filename="unhappy\unhappy1.ans"/></testcase><testcase timelimit="0.1" memorylimit="256000" score="10"><input filename="unhappy\unhappy2.in"/><output filename="unhappy\unhappy2.ans"/></testcase><testcase timelimit="0.1" memorylimit="256000" score="10"><input filename="unhappy\unhappy3.in"/><output filename="unhappy\unhappy3.ans"/></testcase><testcase timelimit="0.1" memorylimit="256000" score="10"><input filename="unhappy\unhappy4.in"/><output filename="unhappy\unhappy4.ans"/></testcase><testcase timelimit="0.1" memorylimit="256000" score="10"><input filename="unhappy\unhappy5.in"/><output filename="unhappy\unhappy5.ans"/></testcase><testcase timelimit="0.1" memorylimit="256000" score="10"><input filename="unhappy\unhappy6.in"/><output filename="unhappy\unhappy6.ans"/></testcase><testcase timelimit="0.1" memorylimit="256000" score="10"><input filename="unhappy\unhappy7.in"/><output filename="unhappy\unhappy7.ans"/></testcase><testcase timelimit="0.1" memorylimit="256000" score="10"><input filename="unhappy\unhappy8.in"/><output filename="unhappy\unhappy8.ans"/></testcase><testcase timelimit="0.1" memorylimit="256000" score="10"><input filename="unhappy\unhappy9.in"/><output filename="unhappy\unhappy9.ans"/></testcase><testcase timelimit="0.1" memorylimit="256000" score="10"><input filename="unhappy\unhappy10.in"/><output filename="unhappy\unhappy10.ans"/></testcase></problem><problem title="试题 2" filename="peanuts" comparetype="1" customchecker=""><input filename="peanuts.in"/><output filename="peanuts.out"/><testcase timelimit="0.1" memorylimit="256000" score="10"><input filename="peanuts\peanuts1.in"/><output filename="peanuts\peanuts1.ans"/></testcase><testcase timelimit="0.1" memorylimit="256000" score="10"><input filename="peanuts\peanuts2.in"/><output filename="peanuts\peanuts2.ans"/></testcase><testcase timelimit="0.1" memorylimit="256000" score="10"><input filename="peanuts\peanuts3.in"/><output filename="peanuts\peanuts3.ans"/></testcase><testcase timelimit="0.1" memorylimit="256000" score="10"><input filename="peanuts\peanuts4.in"/><output filename="peanuts\peanuts4.ans"/></testcase><testcase timelimit="0.1" memorylimit="256000" score="10"><input filename="peanuts\peanuts5.in"/><output filename="peanuts\peanuts5.ans"/></testcase><testcase timelimit="0.1" memorylimit="256000" score="10"><input filename="peanuts\peanuts6.in"/><output filename="peanuts\peanuts6.ans"/></testcase><testcase timelimit="0.1" memorylimit="256000" score="10"><input filename="peanuts\peanuts7.in"/><output filename="peanuts\peanuts7.ans"/></testcase><testcase timelimit="0.1" memorylimit="256000" score="10"><input filename="peanuts\peanuts8.in"/><output filename="peanuts\peanuts8.ans"/></testcase><testcase timelimit="0.1" memorylimit="256000" score="10"><input filename="peanuts\peanuts9.in"/><output filename="peanuts\peanuts9.ans"/></testcase><testcase timelimit="0.1" memorylimit="256000" score="10"><input filename="peanuts\peanuts10.in"/><output filename="peanuts\peanuts10.ans"/></testcase></problem><problem title="试题 3" filename="fbi" comparetype="1" customchecker=""><input filename="fbi.in"/><output filename="fbi.out"/><testcase timelimit="0.1" memorylimit="256000" score="10"><input filename="fbi\fbi1.in"/><output filename="fbi\fbi1.ans"/></testcase><testcase timelimit="0.1" memorylimit="256000" score="10"><input filename="fbi\fbi2.in"/><output filename="fbi\fbi2.ans"/></testcase><testcase timelimit="0.1" memorylimit="256000" score="10"><input filename="fbi\fbi3.in"/><output filename="fbi\fbi3.ans"/></testcase><testcase timelimit="0.1" memorylimit="256000" score="10"><input filename="fbi\fbi4.in"/><output filename="fbi\fbi4.ans"/></testcase><testcase timelimit="0.1" memorylimit="256000" score="10"><input filename="fbi\fbi5.in"/><output filename="fbi\fbi5.ans"/></testcase><testcase timelimit="0.1" memorylimit="256000" score="10"><input filename="fbi\fbi6.in"/><output filename="fbi\fbi6.ans"/></testcase><testcase timelimit="0.1" memorylimit="256000" score="10"><input filename="fbi\fbi7.in"/><output filename="fbi\fbi7.ans"/></testcase><testcase timelimit="0.1" memorylimit="256000" score="10"><input filename="fbi\fbi8.in"/><output filename="fbi\fbi8.ans"/></testcase><testcase timelimit="0.1" memorylimit="256000" score="10"><input filename="fbi\fbi9.in"/><output filename="fbi\fbi9.ans"/></testcase><testcase timelimit="0.1" memorylimit="256000" score="10"><input filename="fbi\fbi10.in"/><output filename="fbi\fbi10.ans"/></testcase></problem><problem title="试题 4" filename="martian" comparetype="1" customchecker=""><input filename="martian.in"/><output filename="martian.out"/><testcase timelimit="0.1" memorylimit="256000" score="10"><input filename="martian\martian1.in"/><output filename="martian\martian1.ans"/></testcase><testcase timelimit="0.1" memorylimit="256000" score="10"><input filename="martian\martian2.in"/><output filename="martian\martian2.ans"/></testcase><testcase timelimit="0.1" memorylimit="256000" score="10"><input filename="martian\martian3.in"/><output filename="martian\martian3.ans"/></testcase><testcase timelimit="0.1" memorylimit="256000" score="10"><input filename="martian\martian4.in"/><output filename="martian\martian4.ans"/></testcase><testcase timelimit="0.1" memorylimit="256000" score="10"><input filename="martian\martian5.in"/><output filename="martian\martian5.ans"/></testcase><testcase timelimit="0.1" memorylimit="256000" score="10"><input filename="martian\martian6.in"/><output filename="martian\martian6.ans"/></testcase><testcase timelimit="0.1" memorylimit="256000" score="10"><input filename="martian\martian7.in"/><output filename="martian\martian7.ans"/></testcase><testcase timelimit="0.1" memorylimit="256000" score="10"><input filename="martian\martian8.in"/><output filename="martian\martian8.ans"/></testcase><testcase timelimit="0.1" memorylimit="256000" score="10"><input filename="martian\martian9.in"/><output filename="martian\martian9.ans"/></testcase><testcase timelimit="0.1" memorylimit="256000" score="10"><input filename="martian\martian10.in"/><output filename="martian\martian10.ans"/></testcase></problem></contest></cena>
